LICENSE
MANIFEST.in
README.md
setup.cfg
setup.py
django_postgres_dbdefaults.egg-info/PKG-INFO
django_postgres_dbdefaults.egg-info/SOURCES.txt
django_postgres_dbdefaults.egg-info/dependency_links.txt
django_postgres_dbdefaults.egg-info/not-zip-safe
django_postgres_dbdefaults.egg-info/top_level.txt
postgresql_dbdefaults/__init__.py
postgresql_dbdefaults/base.py
postgresql_dbdefaults/client.py
postgresql_dbdefaults/creation.py
postgresql_dbdefaults/features.py
postgresql_dbdefaults/introspection.py
postgresql_dbdefaults/operations.py
postgresql_dbdefaults/schema.py
postgresql_dbdefaults/utils.py
postgresql_dbdefaults/version.py