Metadata-Version: 1.1
Name: django-postgres-dbdefaults
Version: 0.1.1
Summary: Maintain database defaults in django sql migrations (instead of dropping them).
Home-page: https://github.com/ringly/django-postgres-dbdefaults
Author: Peter Coles
Author-email: peter@ringly.com
License: UNKNOWN
Platform: UNKNOWN
Classifier: Development Status :: 2 - Pre-Alpha
Classifier: Environment :: Web Environment
Classifier: Intended Audience :: Developers
Classifier: License :: OSI Approved :: MIT License
Classifier: Operating System :: OS Independent
Classifier: Programming Language :: Python
Classifier: Programming Language :: Python :: 2.7
Classifier: Programming Language :: Python :: 3.3
Classifier: Programming Language :: Python :: 3.4
Classifier: Framework :: Django
